ace_tools/__init__.py
ace_tools/tools.py
ace_tools_lite-0.1.1.dist-info/LICENSE
ace_tools_lite-0.1.1.dist-info/METADATA
ace_tools_lite-0.1.1.dist-info/WHEEL
ace_tools_lite-0.1.1.dist-info/RECORD
