Metadata-Version: 2.3
Name: ace-tools-lite
Version: 0.1.1
Summary: 
License: MIT
Author: Alex Zankevich
Author-email: zancudero@gmail.com
Requires-Python: >=3.10
Classifier: License :: OSI Approved :: MIT License
Classifier: Programming Language :: Python :: 3
Classifier: Programming Language :: Python :: 3.10
Classifier: Programming Language :: Python :: 3.11
Classifier: Programming Language :: Python :: 3.12
Classifier: Programming Language :: Python :: 3.13
Requires-Dist: matplotlib (>=3.10.3,<4.0.0)
Requires-Dist: pandas (>=2.2.3,<3.0.0)
